urllib2_prior_auth.py
urllib2_prior_auth-0.2.0.dist-info/top_level.txt
urllib2_prior_auth-0.2.0.dist-info/METADATA
urllib2_prior_auth-0.2.0.dist-info/DESCRIPTION.rst
urllib2_prior_auth-0.2.0.dist-info/metadata.json
urllib2_prior_auth-0.2.0.dist-info/WHEEL
urllib2_prior_auth-0.2.0.dist-info/RECORD
